README.md
setup.cfg
setup.py
enhanced_multiprocessing/__init__.py
enhanced_multiprocessing/cache_manager.py
enhanced_multiprocessing/progress_bar.py
enhanced_multiprocessing/signals.py
enhanced_multiprocessing.egg-info/PKG-INFO
enhanced_multiprocessing.egg-info/SOURCES.txt
enhanced_multiprocessing.egg-info/dependency_links.txt
enhanced_multiprocessing.egg-info/requires.txt
enhanced_multiprocessing.egg-info/top_level.txt