Metadata-Version: 1.1
Name: enhanced-multiprocessing
Version: 1.0
Summary: A wrapper around Python's multiprocessing, providing support for tqdm progress bars and shared arguments
Home-page: https://github.com/krassowski/enhanced-multiprocessing
Author: Michal Krassowski
Author-email: krassowski.michal+pypi@gmail.com
License: MIT
Keywords: multiprocessing,multiprocess,progress,progressbar,bar,enhanced
Platform: UNKNOWN
Classifier: Development Status :: 5 - Production/Stable
Classifier: License :: OSI Approved :: MIT License
Classifier: Operating System :: POSIX :: Linux
Classifier: Topic :: Utilities
Classifier: Topic :: Software Development :: Libraries :: Python Modules
Classifier: Intended Audience :: Developers
Classifier: Intended Audience :: Science/Research
Classifier: Programming Language :: Python :: 3.7
